Verilog/pointint.v
module Area(
	input signed [11:0] ax, input signed [11:0] ay,// 32, 51
	input signed [11:0] bx, input signed [11:0] by,// 0, 0
	input signed [11:0] cx, input signed [11:0] cy,// 69, 54
	output signed [82:0] out
);
	//(((m1) - (m2)) + ((m3) - (m4)) + ((m5) - (m6)));
	wire signed [12:0] m1;// 0
	wire signed [12:0] m2;// 0
	wire signed [12:0] m3;// 3519
	wire signed [12:0] m4;// 1728
	wire signed [12:0] m5;// 0
	wire signed [12:0] m6;// 0

	wire signed [23:0] s1;
	wire signed [23:0] s2;
	wire signed [23:0] s3;
	
	wire signed [82:0] sumf;

	assign m1 = ax * by;
	assign m2 = ay * bx;
	assign m3 = ay * cx;	

	assign m4 = ax * cy;
	assign m5 = bx * cy;
	assign m6 = by * cx;

	assign s1 = m1 - m2; 
	assign s2 = m3 - m4;
	assign s3 = m5 - m6;

	assign sumf = s1 + s2 + s3;
	
	assign out = sumf;

endmodule

module isintriangule(
	input signed [11:0] px,
	input signed [11:0] py,
	input signed [11:0] ax,
	input signed [11:0] ay,
	input signed [11:0] bx,
	input signed [11:0] by,
	input signed [11:0] cx,
	input signed [11:0] cy,
	output signed out
);
	wire signed [82:0] b1;
	wire signed [82:0] b2;
	wire signed [82:0] b3;

	Area A1(px, py, bx, by, cx, cy, b1);
	Area A2(ax, ay, px, py, cx, cy, b2);
	Area A3(ax, ay, bx, by, px, py, b3);

	assign out = (b1 > 0) && (b2 > 0) && (b3 > 0);

endmodule

module principal;

	integer signed input_file;
	integer	signed output_file;

	reg signed [90:0] value;

	reg signed [11:0] ax; reg signed [11:0] ay;
	reg signed [11:0] bx; reg signed [11:0] by;
	reg signed [11:0] cx; reg signed [11:0] cy;
	reg signed [11:0] px; reg signed [11:0] py;
	reg signed [11:0] r;
	

	isintriangule A(px, py, ax, ay, bx, by, cx, cy, out);

	initial begin
		$dumpvars(0, A);		
	
		input_file  = $fopen("Result.txt", "r");
		output_file = $fopen("Result_verilog.txt", "w");

		if(input_file == 0) begin
			$display("Cannot open input_file. Does it exists?");
			$finish;
		end
	end

	always #2 begin
		if(!$feof(input_file)) begin			
			value = $fscanf(input_file, "A(%d, %d),  B(%d, %d), C(%d, %d),  P(%d, %d) = %d\n", ax, ay, bx, by, cx, cy, px, py, r);
			#1			
			$fwrite(output_file, "A(%0d, %0d),  B(%0d, %0d), C(%0d, %0d),  P(%0d, %0d) = %0d\n", ax, ay, bx, by, cx, cy, px, py, out);
		end
		else begin
			$finish;
		end
	end

endmodule

Verilog/dump.vcd
$date
	Sat Jun 25 09:42:51 2016
$end
$version
	Icarus Verilog
$end
$timescale
	1s
$end
$scope module principal $end
$scope module A $end
$var wire 12 ! ax [11:0] $end
$var wire 12 " ay [11:0] $end
$var wire 12 # bx [11:0] $end
$var wire 12 $ by [11:0] $end
$var wire 12 % cx [11:0] $end
$var wire 12 & cy [11:0] $end
$var wire 1 ' out $end
$var wire 12 ( px [11:0] $end
$var wire 12 ) py [11:0] $end
$var wire 83 * b3 [82:0] $end
$var wire 83 + b2 [82:0] $end
$var wire 83 , b1 [82:0] $end
$scope module A1 $end
$var wire 12 - ax [11:0] $end
$var wire 12 . ay [11:0] $end
$var wire 12 / bx [11:0] $end
$var wire 12 0 by [11:0] $end
$var wire 12 1 cx [11:0] $end
$var wire 12 2 cy [11:0] $end
$var wire 83 3 out [82:0] $end
$var wire 83 4 sumf [82:0] $end
$var wire 24 5 s3 [23:0] $end
$var wire 24 6 s2 [23:0] $end
$var wire 24 7 s1 [23:0] $end
$var wire 13 8 m6 [12:0] $end
$var wire 13 9 m5 [12:0] $end
$var wire 13 : m4 [12:0] $end
$var wire 13 ; m3 [12:0] $end
$var wire 13 < m2 [12:0] $end
$var wire 13 = m1 [12:0] $end
$upscope $end
$scope module A2 $end
$var wire 12 > ax [11:0] $end
$var wire 12 ? ay [11:0] $end
$var wire 12 @ bx [11:0] $end
$var wire 12 A by [11:0] $end
$var wire 12 B cx [11:0] $end
$var wire 12 C cy [11:0] $end
$var wire 83 D out [82:0] $end
$var wire 83 E sumf [82:0] $end
$var wire 24 F s3 [23:0] $end
$var wire 24 G s2 [23:0] $end
$var wire 24 H s1 [23:0] $end
$var wire 13 I m6 [12:0] $end
$var wire 13 J m5 [12:0] $end
$var wire 13 K m4 [12:0] $end
$var wire 13 L m3 [12:0] $end
$var wire 13 M m2 [12:0] $end
$var wire 13 N m1 [12:0] $end
$upscope $end
$scope module A3 $end
$var wire 12 O ax [11:0] $end
$var wire 12 P ay [11:0] $end
$var wire 12 Q bx [11:0] $end
$var wire 12 R by [11:0] $end
$var wire 12 S cx [11:0] $end
$var wire 12 T cy [11:0] $end
$var wire 83 U out [82:0] $end
$var wire 83 V sumf [82:0] $end
$var wire 24 W s3 [23:0] $end
$var wire 24 X s2 [23:0] $end
$var wire 24 Y s1 [23:0] $end
$var wire 13 Z m6 [12:0] $end
$var wire 13 [ m5 [12:0] $end
$var wire 13 \ m4 [12:0] $end
$var wire 13 ] m3 [12:0] $end
$var wire 13 ^ m2 [12:0] $end
$var wire 13 _ m1 [12:0] $end
$upscope $end
$upscope $end
$upscope $end
$enddefinitions $end
#0
$dumpvars
bx _
bx ^
bx ]
bx \
bx [
bx Z
bx Y
bx X
bx W
bx V
bx U
bx T
bx S
bx R
bx Q
bx P
bx O
bx N
bx M
bx L
bx K
bx J
bx I
bx H
bx G
bx F
bx E
bx D
bx C
bx B
bx A
bx @
bx ?
bx >
bx =
bx <
bx ;
bx :
bx 9
bx 8
bx 7
bx 6
bx 5
bx 4
bx 3
bx 2
bx 1
bx 0
bx /
bx .
bx -
bx ,
bx +
bx *
bx )
bx (
x'
bx &
bx %
bx $
bx #
bx "
bx !
$end
#2
0'
b100010100 ,
b100010100 3
b100010100 4
b0 7
b0 <
b0 6
b0 ;
b11011111111 +
b11011111111 D
b11011111111 E
b0 H
b0 N
b0 F
b0 I
b11111111111111111111111111111111111111111111111111111111111111111111111110100101011 *
b11111111111111111111111111111111111111111111111111111111111111111111111110100101011 U
b11111111111111111111111111111111111111111111111111111111111111111111111110100101011 V
b0 X
b0 \
b0 W
b0 [
b0 )
b0 .
b0 A
b0 T
b0 =
b0 :
b0 M
b0 J
b0 ]
b0 Z
b0 (
b0 -
b0 @
b0 S
b100010100 5
b10011011010 9
b11011111111 G
b11011000000 K
b110110 &
b110110 2
b110110 C
b1111000110 8
b110110111111 L
b1000101 %
b1000101 1
b1000101 B
b111111111111110100101011 Y
b111000000 _
b1110 $
b1110 0
b1110 R
b10010010101 ^
b10111 #
b10111 /
b10111 Q
b110011 "
b110011 ?
b110011 P
b100000 !
b100000 >
b100000 O
#5
b1110 7
b1110 =
b11101100 ,
b11101100 3
b11101100 4
b111111111111111111001010 6
b110110 :
b111111111111111111001101 H
b110011 M
b11100000010 +
b11100000010 D
b11100000010 E
b110110 F
b110110 J
b110011 X
b110011 ]
b11111111111111111111111111111111111111111111111111111111111111111111111110101010000 *
b11111111111111111111111111111111111111111111111111111111111111111111111110101010000 U
b11111111111111111111111111111111111111111111111111111111111111111111111110101010000 V
b111111111111111111110010 W
b1110 Z
b1 (
b1 -
b1 @
b1 S
#8
b11100 7
b11100 =
b11000100 ,
b11000100 3
b11000100 4
b111111111111111110010100 6
b1101100 :
b111111111111111110011010 H
b1100110 M
b11100000101 +
b11100000101 D
b11100000101 E
b1101100 F
b1101100 J
b1100110 X
b1100110 ]
b11111111111111111111111111111111111111111111111111111111111111111111111110101110101 *
b11111111111111111111111111111111111111111111111111111111111111111111111110101110101 U
b11111111111111111111111111111111111111111111111111111111111111111111111110101110101 V
b111111111111111111100100 W
b11100 Z
b10 (
b10 -
b10 @
b10 S
#11
b101010 7
b101010 =
b10011100 ,
b10011100 3
b10011100 4
b111111111111111101011110 6
b10100010 :
b111111111111111101100111 H
b10011001 M
b11100001000 +
b11100001000 D
b11100001000 E
b10100010 F
b10100010 J
b10011001 X
b10011001 ]
b11111111111111111111111111111111111111111111111111111111111111111111111110110011010 *
b11111111111111111111111111111111111111111111111111111111111111111111111110110011010 U
b11111111111111111111111111111111111111111111111111111111111111111111111110110011010 V
b111111111111111111010110 W
b101010 Z
b11 (
b11 -
b11 @
b11 S
#14
b111000 7
b111000 =
b1110100 ,
b1110100 3
b1110100 4
b111111111111111100101000 6
b11011000 :
b111111111111111100110100 H
b11001100 M
b11100001011 +
b11100001011 D
b11100001011 E
b11011000 F
b11011000 J
b11001100 X
b11001100 ]
b11111111111111111111111111111111111111111111111111111111111111111111111110110111111 *
b11111111111111111111111111111111111111111111111111111111111111111111111110110111111 U
b11111111111111111111111111111111111111111111111111111111111111111111111110110111111 V
b111111111111111111001000 W
b111000 Z
b100 (
b100 -
b100 @
b100 S
#17
b1000110 7
b1000110 =
b1001100 ,
b1001100 3
b1001100 4
b111111111111111011110010 6
b100001110 :
b111111111111111100000001 H
b11111111 M
b11100001110 +
b11100001110 D
b11100001110 E
b100001110 F
b100001110 J
b11111111 X
b11111111 ]
b11111111111111111111111111111111111111111111111111111111111111111111111110111100100 *
b11111111111111111111111111111111111111111111111111111111111111111111111110111100100 U
b11111111111111111111111111111111111111111111111111111111111111111111111110111100100 V
b111111111111111110111010 W
b1000110 Z
b101 (
b101 -
b101 @
b101 S
#20
b1010100 7
b1010100 =
b100100 ,
b100100 3
b100100 4
b111111111111111010111100 6
b101000100 :
b111111111111111011001110 H
b100110010 M
b11100010001 +
b11100010001 D
b11100010001 E
b101000100 F
b101000100 J
b100110010 X
b100110010 ]
b11111111111111111111111111111111111111111111111111111111111111111111111111000001001 *
b11111111111111111111111111111111111111111111111111111111111111111111111111000001001 U
b11111111111111111111111111111111111111111111111111111111111111111111111111000001001 V
b111111111111111110101100 W
b1010100 Z
b110 (
b110 -
b110 @
b110 S
#23
b1100010 7
b1100010 =
b11111111111111111111111111111111111111111111111111111111111111111111111111111111100 ,
b11111111111111111111111111111111111111111111111111111111111111111111111111111111100 3
b11111111111111111111111111111111111111111111111111111111111111111111111111111111100 4
b111111111111111010000110 6
b101111010 :
b111111111111111010011011 H
b101100101 M
b11100010100 +
b11100010100 D
b11100010100 E
b101111010 F
b101111010 J
b101100101 X
b101100101 ]
b11111111111111111111111111111111111111111111111111111111111111111111111111000101110 *
b11111111111111111111111111111111111111111111111111111111111111111111111111000101110 U
b11111111111111111111111111111111111111111111111111111111111111111111111111000101110 V
b111111111111111110011110 W
b1100010 Z
b111 (
b111 -
b111 @
b111 S
#26
b1110000 7
b1110000 =
b11111111111111111111111111111111111111111111111111111111111111111111111111111010100 ,
b11111111111111111111111111111111111111111111111111111111111111111111111111111010100 3
b11111111111111111111111111111111111111111111111111111111111111111111111111111010100 4
b111111111111111001010000 6
b110110000 :
b111111111111111001101000 H
b110011000 M
b11100010111 +
b11100010111 D
b11100010111 E
b110110000 F
b110110000 J
b110011000 X
b110011000 ]
b11111111111111111111111111111111111111111111111111111111111111111111111111001010011 *
b11111111111111111111111111111111111111111111111111111111111111111111111111001010011 U
b11111111111111111111111111111111111111111111111111111111111111111111111111001010011 V
b111111111111111110010000 W
b1110000 Z
b1000 (
b1000 -
b1000 @
b1000 S
#29
b1111110 7
b1111110 =
b11111111111111111111111111111111111111111111111111111111111111111111111111110101100 ,
b11111111111111111111111111111111111111111111111111111111111111111111111111110101100 3
b11111111111111111111111111111111111111111111111111111111111111111111111111110101100 4
b111111111111111000011010 6
b111100110 :
b111111111111111000110101 H
b111001011 M
b11100011010 +
b11100011010 D
b11100011010 E
b111100110 F
b111100110 J
b111001011 X
b111001011 ]
b11111111111111111111111111111111111111111111111111111111111111111111111111001111000 *
b11111111111111111111111111111111111111111111111111111111111111111111111111001111000 U
b11111111111111111111111111111111111111111111111111111111111111111111111111001111000 V
b111111111111111110000010 W
b1111110 Z
b1001 (
b1001 -
b1001 @
b1001 S
#32
b10001100 7
b10001100 =
b11111111111111111111111111111111111111111111111111111111111111111111111111110000100 ,
b11111111111111111111111111111111111111111111111111111111111111111111111111110000100 3
b11111111111111111111111111111111111111111111111111111111111111111111111111110000100 4
b111111111111110111100100 6
b1000011100 :
b111111111111111000000010 H
b111111110 M
b11100011101 +
b11100011101 D
b11100011101 E
b1000011100 F
b1000011100 J
b111111110 X
b111111110 ]
b11111111111111111111111111111111111111111111111111111111111111111111111111010011101 *
b11111111111111111111111111111111111111111111111111111111111111111111111111010011101 U
b11111111111111111111111111111111111111111111111111111111111111111111111111010011101 V
b111111111111111101110100 W
b10001100 Z
b1010 (
b1010 -
b1010 @
b1010 S
#35
b10011010 7
b10011010 =
b11111111111111111111111111111111111111111111111111111111111111111111111111101011100 ,
b11111111111111111111111111111111111111111111111111111111111111111111111111101011100 3
b11111111111111111111111111111111111111111111111111111111111111111111111111101011100 4
b111111111111110110101110 6
b1001010010 :
b111111111111110111001111 H
b1000110001 M
b11100100000 +
b11100100000 D
b11100100000 E
b1001010010 F
b1001010010 J
b1000110001 X
b1000110001 ]
b11111111111111111111111111111111111111111111111111111111111111111111111111011000010 *
b11111111111111111111111111111111111111111111111111111111111111111111111111011000010 U
b11111111111111111111111111111111111111111111111111111111111111111111111111011000010 V
b111111111111111101100110 W
b10011010 Z
b1011 (
b1011 -
b1011 @
b1011 S
#38
b10101000 7
b10101000 =
b11111111111111111111111111111111111111111111111111111111111111111111111111100110100 ,
b11111111111111111111111111111111111111111111111111111111111111111111111111100110100 3
b11111111111111111111111111111111111111111111111111111111111111111111111111100110100 4
b111111111111110101111000 6
b1010001000 :
b111111111111110110011100 H
b1001100100 M
b11100100011 +
b11100100011 D
b11100100011 E
b1010001000 F
b1010001000 J
b1001100100 X
b1001100100 ]
b11111111111111111111111111111111111111111111111111111111111111111111111111011100111 *
b11111111111111111111111111111111111111111111111111111111111111111111111111011100111 U
b11111111111111111111111111111111111111111111111111111111111111111111111111011100111 V
b111111111111111101011000 W
b10101000 Z
b1100 (
b1100 -
b1100 @
b1100 S
#41
b10110110 7
b10110110 =
b11111111111111111111111111111111111111111111111111111111111111111111111111100001100 ,
b11111111111111111111111111111111111111111111111111111111111111111111111111100001100 3
b11111111111111111111111111111111111111111111111111111111111111111111111111100001100 4
b111111111111110101000010 6
b1010111110 :
b111111111111110101101001 H
b1010010111 M
b11100100110 +
b11100100110 D
b11100100110 E
b1010111110 F
b1010111110 J
b1010010111 X
b1010010111 ]
b11111111111111111111111111111111111111111111111111111111111111111111111111100001100 *
b11111111111111111111111111111111111111111111111111111111111111111111111111100001100 U
b11111111111111111111111111111111111111111111111111111111111111111111111111100001100 V
b111111111111111101001010 W
b10110110 Z
b1101 (
b1101 -
b1101 @
b1101 S
#44
b11000100 7
b11000100 =
b11111111111111111111111111111111111111111111111111111111111111111111111111011100100 ,
b11111111111111111111111111111111111111111111111111111111111111111111111111011100100 3
b11111111111111111111111111111111111111111111111111111111111111111111111111011100100 4
b111111111111110100001100 6
b1011110100 :
b111111111111110100110110 H
b1011001010 M
b11100101001 +
b11100101001 D
b11100101001 E
b1011110100 F
b1011110100 J
b1011001010 X
b1011001010 ]
b11111111111111111111111111111111111111111111111111111111111111111111111111100110001 *
b11111111111111111111111111111111111111111111111111111111111111111111111111100110001 U
b11111111111111111111111111111111111111111111111111111111111111111111111111100110001 V
b111111111111111100111100 W
b11000100 Z
b1110 (
b1110 -
b1110 @
b1110 S
#47
b11010010 7
b11010010 =
b11111111111111111111111111111111111111111111111111111111111111111111111111010111100 ,
b11111111111111111111111111111111111111111111111111111111111111111111111111010111100 3
b11111111111111111111111111111111111111111111111111111111111111111111111111010111100 4
b111111111111110011010110 6
b1100101010 :
b111111111111110100000011 H
b1011111101 M
b11100101100 +
b11100101100 D
b11100101100 E
b1100101010 F
b1100101010 J
b1011111101 X
b1011111101 ]
b11111111111111111111111111111111111111111111111111111111111111111111111111101010110 *
b11111111111111111111111111111111111111111111111111111111111111111111111111101010110 U
b11111111111111111111111111111111111111111111111111111111111111111111111111101010110 V
b111111111111111100101110 W
b11010010 Z
b1111 (
b1111 -
b1111 @
b1111 S
#50
b11100000 7
b11100000 =
b11111111111111111111111111111111111111111111111111111111111111111111111111010010100 ,
b11111111111111111111111111111111111111111111111111111111111111111111111111010010100 3
b11111111111111111111111111111111111111111111111111111111111111111111111111010010100 4
b111111111111110010100000 6
b1101100000 :
b111111111111110011010000 H
b1100110000 M
b11100101111 +
b11100101111 D
b11100101111 E
b1101100000 F
b1101100000 J
b1100110000 X
b1100110000 ]
b11111111111111111111111111111111111111111111111111111111111111111111111111101111011 *
b11111111111111111111111111111111111111111111111111111111111111111111111111101111011 U
b11111111111111111111111111111111111111111111111111111111111111111111111111101111011 V
b111111111111111100100000 W
b11100000 Z
b10000 (
b10000 -
b10000 @
b10000 S
#53
b11101110 7
b11101110 =
b11111111111111111111111111111111111111111111111111111111111111111111111111001101100 ,
b11111111111111111111111111111111111111111111111111111111111111111111111111001101100 3
b11111111111111111111111111111111111111111111111111111111111111111111111111001101100 4
b111111111111110001101010 6
b1110010110 :
b111111111111110010011101 H
b1101100011 M
b11100110010 +
b11100110010 D
b11100110010 E
b1110010110 F
b1110010110 J
b1101100011 X
b1101100011 ]
b11111111111111111111111111111111111111111111111111111111111111111111111111110100000 *
b11111111111111111111111111111111111111111111111111111111111111111111111111110100000 U
b11111111111111111111111111111111111111111111111111111111111111111111111111110100000 V
b111111111111111100010010 W
b11101110 Z
b10001 (
b10001 -
b10001 @
b10001 S
#56
b11111100 7
b11111100 =
b11111111111111111111111111111111111111111111111111111111111111111111111111001000100 ,
b11111111111111111111111111111111111111111111111111111111111111111111111111001000100 3
b11111111111111111111111111111111111111111111111111111111111111111111111111001000100 4
b111111111111110000110100 6
b1111001100 :
b111111111111110001101010 H
b1110010110 M
b11100110101 +
b11100110101 D
b11100110101 E
b1111001100 F
b1111001100 J
b1110010110 X
b1110010110 ]
b11111111111111111111111111111111111111111111111111111111111111111111111111111000101 *
b11111111111111111111111111111111111111111111111111111111111111111111111111111000101 U
b11111111111111111111111111111111111111111111111111111111111111111111111111111000101 V
b111111111111111100000100 W
b11111100 Z
b10010 (
b10010 -
b10010 @
b10010 S
#59
b100001010 7
b100001010 =
b11111111111111111111111111111111111111111111111111111111111111111111111111000011100 ,
b11111111111111111111111111111111111111111111111111111111111111111111111111000011100 3
b11111111111111111111111111111111111111111111111111111111111111111111111111000011100 4
b111111111111101111111110 6
b10000000010 :
b111111111111110000110111 H
b1111001001 M
b11100111000 +
b11100111000 D
b11100111000 E
b10000000010 F
b10000000010 J
b1111001001 X
b1111001001 ]
b11111111111111111111111111111111111111111111111111111111111111111111111111111101010 *
b11111111111111111111111111111111111111111111111111111111111111111111111111111101010 U
b11111111111111111111111111111111111111111111111111111111111111111111111111111101010 V
b111111111111111011110110 W
b100001010 Z
b10011 (
b10011 -
b10011 @
b10011 S
#62
b100011000 7
b100011000 =
b11111111111111111111111111111111111111111111111111111111111111111111111110111110100 ,
b11111111111111111111111111111111111111111111111111111111111111111111111110111110100 3
b11111111111111111111111111111111111111111111111111111111111111111111111110111110100 4
b111111111111101111001000 6
b10000111000 :
b111111111111110000000100 H
b1111111100 M
b11100111011 +
b11100111011 D
b11100111011 E
b10000111000 F
b10000111000 J
b1111111100 X
b1111111100 ]
b1111 *
b1111 U
b1111 V
b111111111111111011101000 W
b100011000 Z
b10100 (
b10100 -
b10100 @
b10100 S
#65
b100100110 7
b100100110 =
b11111111111111111111111111111111111111111111111111111111111111111111111110111001100 ,
b11111111111111111111111111111111111111111111111111111111111111111111111110111001100 3
b11111111111111111111111111111111111111111111111111111111111111111111111110111001100 4
b111111111111101110010010 6
b10001101110 :
b111111111111101111010001 H
b10000101111 M
b11100111110 +
b11100111110 D
b11100111110 E
b10001101110 F
b10001101110 J
b10000101111 X
b10000101111 ]
b110100 *
b110100 U
b110100 V
b111111111111111011011010 W
b100100110 Z
b10101 (
b10101 -
b10101 @
b10101 S
#68
b100110100 7
b100110100 =
b11111111111111111111111111111111111111111111111111111111111111111111111110110100100 ,
b11111111111111111111111111111111111111111111111111111111111111111111111110110100100 3
b11111111111111111111111111111111111111111111111111111111111111111111111110110100100 4
b111111111111101101011100 6
b10010100100 :
b111111111111101110011110 H
b10001100010 M
b11101000001 +
b11101000001 D
b11101000001 E
b10010100100 F
b10010100100 J
b10001100010 X
b10001100010 ]
b1011001 *
b1011001 U
b1011001 V
b111111111111111011001100 W
b100110100 Z
b10110 (
b10110 -
b10110 @
b10110 S
#71
b101000010 7
b101000010 =
b11111111111111111111111111111111111111111111111111111111111111111111111110101111100 ,
b11111111111111111111111111111111111111111111111111111111111111111111111110101111100 3
b11111111111111111111111111111111111111111111111111111111111111111111111110101111100 4
b111111111111101100100110 6
b10011011010 :
b111111111111101101101011 H
b10010010101 M
b11101000100 +
b11101000100 D
b11101000100 E
b10011011010 F
b10011011010 J
b10010010101 X
b10010010101 ]
b1111110 *
b1111110 U
b1111110 V
b111111111111111010111110 W
b101000010 Z
b10111 (
b10111 -
b10111 @
b10111 S
#74
b101010000 7
b101010000 =
b11111111111111111111111111111111111111111111111111111111111111111111111110101010100 ,
b11111111111111111111111111111111111111111111111111111111111111111111111110101010100 3
b11111111111111111111111111111111111111111111111111111111111111111111111110101010100 4
b111111111111101011110000 6
b10100010000 :
b111111111111101100111000 H
b10011001000 M
b11101000111 +
b11101000111 D
b11101000111 E
b10100010000 F
b10100010000 J
b10011001000 X
b10011001000 ]
b10100011 *
b10100011 U
b10100011 V
b111111111111111010110000 W
b101010000 Z
b11000 (
b11000 -
b11000 @
b11000 S
#77
b101011110 7
b101011110 =
b11111111111111111111111111111111111111111111111111111111111111111111111110100101100 ,
b11111111111111111111111111111111111111111111111111111111111111111111111110100101100 3
b11111111111111111111111111111111111111111111111111111111111111111111111110100101100 4
b111111111111101010111010 6
b10101000110 :
b111111111111101100000101 H
b10011111011 M
b11101001010 +
b11101001010 D
b11101001010 E
b10101000110 F
b10101000110 J
b10011111011 X
b10011111011 ]
b11001000 *
b11001000 U
b11001000 V
b111111111111111010100010 W
b101011110 Z
b11001 (
b11001 -
b11001 @
b11001 S
#80
b101101100 7
b101101100 =
b11111111111111111111111111111111111111111111111111111111111111111111111110100000100 ,
b11111111111111111111111111111111111111111111111111111111111111111111111110100000100 3
b11111111111111111111111111111111111111111111111111111111111111111111111110100000100 4
b111111111111101010000100 6
b10101111100 :
b111111111111101011010010 H
b10100101110 M
b11101001101 +
b11101001101 D
b11101001101 E
b10101111100 F
b10101111100 J
b10100101110 X
b10100101110 ]
b11101101 *
b11101101 U
b11101101 V
b111111111111111010010100 W
b101101100 Z
b11010 (
b11010 -
b11010 @
b11010 S
#83
b101111010 7
b101111010 =
b11111111111111111111111111111111111111111111111111111111111111111111111110011011100 ,
b11111111111111111111111111111111111111111111111111111111111111111111111110011011100 3
b11111111111111111111111111111111111111111111111111111111111111111111111110011011100 4
b111111111111101001001110 6
b10110110010 :
b111111111111101010011111 H
b10101100001 M
b11101010000 +
b11101010000 D
b11101010000 E
b10110110010 F
b10110110010 J
b10101100001 X
b10101100001 ]
b100010010 *
b100010010 U
b100010010 V
b111111111111111010000110 W
b101111010 Z
b11011 (
b11011 -
b11011 @
b11011 S
#86
b110001000 7
b110001000 =
b11111111111111111111111111111111111111111111111111111111111111111111111110010110100 ,
b11111111111111111111111111111111111111111111111111111111111111111111111110010110100 3
b11111111111111111111111111111111111111111111111111111111111111111111111110010110100 4
b111111111111101000011000 6
b10111101000 :
b111111111111101001101100 H
b10110010100 M
b11101010011 +
b11101010011 D
b11101010011 E
b10111101000 F
b10111101000 J
b10110010100 X
b10110010100 ]
b100110111 *
b100110111 U
b100110111 V
b111111111111111001111000 W
b110001000 Z
b11100 (
b11100 -
b11100 @
b11100 S
#89
b110010110 7
b110010110 =
b11111111111111111111111111111111111111111111111111111111111111111111111110010001100 ,
b11111111111111111111111111111111111111111111111111111111111111111111111110010001100 3
b11111111111111111111111111111111111111111111111111111111111111111111111110010001100 4
b111111111111100111100010 6
b11000011110 :
b111111111111101000111001 H
b10111000111 M
b11101010110 +
b11101010110 D
b11101010110 E
b11000011110 F
b11000011110 J
b10111000111 X
b10111000111 ]
b101011100 *
b101011100 U
b101011100 V
b111111111111111001101010 W
b110010110 Z
b11101 (
b11101 -
b11101 @
b11101 S
#92
b110100100 7
b110100100 =
b11111111111111111111111111111111111111111111111111111111111111111111111110001100100 ,
b11111111111111111111111111111111111111111111111111111111111111111111111110001100100 3
b11111111111111111111111111111111111111111111111111111111111111111111111110001100100 4
b111111111111100110101100 6
b11001010100 :
b111111111111101000000110 H
b10111111010 M
b11101011001 +
b11101011001 D
b11101011001 E
b11001010100 F
b11001010100 J
b10111111010 X
b10111111010 ]
b110000001 *
b110000001 U
b110000001 V
b111111111111111001011100 W
b110100100 Z
b11110 (
b11110 -
b11110 @
b11110 S
#95
b110110010 7
b110110010 =
b11111111111111111111111111111111111111111111111111111111111111111111111110000111100 ,
b11111111111111111111111111111111111111111111111111111111111111111111111110000111100 3
b11111111111111111111111111111111111111111111111111111111111111111111111110000111100 4
b111111111111100101110110 6
b11010001010 :
b111111111111100111010011 H
b11000101101 M
b11101011100 +
b11101011100 D
b11101011100 E
b11010001010 F
b11010001010 J
b11000101101 X
b11000101101 ]
b110100110 *
b110100110 U
b110100110 V
b111111111111111001001110 W
b110110010 Z
b11111 (
b11111 -
b11111 @
b11111 S
#98
b111000000 7
b111000000 =
b11111111111111111111111111111111111111111111111111111111111111111111111110000010100 ,
b11111111111111111111111111111111111111111111111111111111111111111111111110000010100 3
b11111111111111111111111111111111111111111111111111111111111111111111111110000010100 4
b111111111111100101000000 6
b11011000000 :
b111111111111100110100000 H
b11001100000 M
b11101011111 +
b11101011111 D
b11101011111 E
b11011000000 F
b11011000000 J
b11001100000 X
b11001100000 ]
b111001011 *
b111001011 U
b111001011 V
b111111111111111001000000 W
b111000000 Z
b100000 (
b100000 -
b100000 @
b100000 S
#101
b111001110 7
b111001110 =
b11111111111111111111111111111111111111111111111111111111111111111111111101111101100 ,
b11111111111111111111111111111111111111111111111111111111111111111111111101111101100 3
b11111111111111111111111111111111111111111111111111111111111111111111111101111101100 4
b111111111111100100001010 6
b11011110110 :
b111111111111100101101101 H
b11010010011 M
b11101100010 +
b11101100010 D
b11101100010 E
b11011110110 F
b11011110110 J
b11010010011 X
b11010010011 ]
b111110000 *
b111110000 U
b111110000 V
b111111111111111000110010 W
b111001110 Z
b100001 (
b100001 -
b100001 @
b100001 S
#104
b111011100 7
b111011100 =
b11111111111111111111111111111111111111111111111111111111111111111111111101111000100 ,
b11111111111111111111111111111111111111111111111111111111111111111111111101111000100 3
b11111111111111111111111111111111111111111111111111111111111111111111111101111000100 4
b111111111111100011010100 6
b11100101100 :
b111111111111100100111010 H
b11011000110 M
b11101100101 +
b11101100101 D
b11101100101 E
b11100101100 F
b11100101100 J
b11011000110 X
b11011000110 ]
b1000010101 *
b1000010101 U
b1000010101 V
b111111111111111000100100 W
b111011100 Z
b100010 (
b100010 -
b100010 @
b100010 S
#107
b111101010 7
b111101010 =
b11111111111111111111111111111111111111111111111111111111111111111111111101110011100 ,
b11111111111111111111111111111111111111111111111111111111111111111111111101110011100 3
b11111111111111111111111111111111111111111111111111111111111111111111111101110011100 4
b111111111111100010011110 6
b11101100010 :
b111111111111100100000111 H
b11011111001 M
b11101101000 +
b11101101000 D
b11101101000 E
b11101100010 F
b11101100010 J
b11011111001 X
b11011111001 ]
b1000111010 *
b1000111010 U
b1000111010 V
b111111111111111000010110 W
b111101010 Z
b100011 (
b100011 -
b100011 @
b100011 S
#110
b111111000 7
b111111000 =
b11111111111111111111111111111111111111111111111111111111111111111111111101101110100 ,
b11111111111111111111111111111111111111111111111111111111111111111111111101101110100 3
b11111111111111111111111111111111111111111111111111111111111111111111111101101110100 4
b111111111111100001101000 6
b11110011000 :
b111111111111100011010100 H
b11100101100 M
b11101101011 +
b11101101011 D
b11101101011 E
b11110011000 F
b11110011000 J
b11100101100 X
b11100101100 ]
b1001011111 *
b1001011111 U
b1001011111 V
b111111111111111000001000 W
b111111000 Z
b100100 (
b100100 -
b100100 @
b100100 S
#113
b1000000110 7
b1000000110 =
b11111111111111111111111111111111111111111111111111111111111111111111111101101001100 ,
b11111111111111111111111111111111111111111111111111111111111111111111111101101001100 3
b11111111111111111111111111111111111111111111111111111111111111111111111101101001100 4
b111111111111100000110010 6
b11111001110 :
b111111111111100010100001 H
b11101011111 M
b11101101110 +
b11101101110 D
b11101101110 E
b11111001110 F
b11111001110 J
b11101011111 X
b11101011111 ]
b1010000100 *
b1010000100 U
b1010000100 V
b111111111111110111111010 W
b1000000110 Z
b100101 (
b100101 -
b100101 @
b100101 S
#116
b1000010100 7
b1000010100 =
b11111111111111111111111111111111111111111111111111111111111111111111111101100100100 ,
b11111111111111111111111111111111111111111111111111111111111111111111111101100100100 3
b11111111111111111111111111111111111111111111111111111111111111111111111101100100100 4
b111111111111011111111100 6
b100000000100 :
b111111111111100001101110 H
b11110010010 M
b11101110001 +
b11101110001 D
b11101110001 E
b100000000100 F
b100000000100 J
b11110010010 X
b11110010010 ]
b1010101001 *
b1010101001 U
b1010101001 V
b111111111111110111101100 W
b1000010100 Z
b100110 (
b100110 -
b100110 @
b100110 S
